dhivehi_unicode/__init__.py
dhivehi_unicode/unicode.py
dhivehi_unicode-1.0.3.dist-info/METADATA
dhivehi_unicode-1.0.3.dist-info/WHEEL
dhivehi_unicode-1.0.3.dist-info/top_level.txt
dhivehi_unicode-1.0.3.dist-info/RECORD
