Metadata-Version: 2.1
Name: dhivehi-unicode
Version: 1.0.3
Summary: Python Dhivehi (Thaana) ASCII, accent to unicode converter
Home-page: https://github.com/medo-mi/dhivehi_unicode
Author: Mohamed Ismail (medo)
Author-email: <modeissey@gmail.com>
License: UNKNOWN
Keywords: Dhivehi,Thaana
Platform: UNKNOWN
Classifier: Development Status :: 4 - Beta
Classifier: Intended Audience :: Developers
Classifier: Programming Language :: Python :: 3
Classifier: Operating System :: Unix
Classifier: Operating System :: MacOS :: MacOS X
Classifier: Operating System :: Microsoft :: Windows
